README.md
setup.py
mexp/__init__.py
mexp/manager.py
mexp.egg-info/PKG-INFO
mexp.egg-info/SOURCES.txt
mexp.egg-info/dependency_links.txt
mexp.egg-info/requires.txt
mexp.egg-info/top_level.txt