Metadata-Version: 2.1
Name: mexp
Version: 0.0.1
Summary: Filter list using properties
Home-page: https://github.com/IbrahimABBAS85/mexp
Author: Ibrahim Abbas
Author-email: i.abbas85@gmail.com
License: UNKNOWN
Platform: UNKNOWN
Classifier: Programming Language :: Python :: 3
Classifier: License :: OSI Approved :: MIT License
Classifier: Operating System :: OS Independent
Requires-Python: >=3.6
